scriptbook/__init__.py
scriptbook/cli.py
scriptbook/main.py
scriptbook/core/__init__.py
scriptbook/core/file_scanner.py
scriptbook/core/markdown_parser.py
scriptbook/core/plugin_manager.py
scriptbook/core/script_executor.py
scriptbook/models/__init__.py
scriptbook/models/schemas.py
scriptbook/plugins/dark-theme/manifest.json
scriptbook/plugins/dark-theme/style.css
scriptbook/plugins/default/manifest.json
scriptbook/plugins/default/style.css
scriptbook/routers/__init__.py
scriptbook/routers/markdown.py
scriptbook/routers/plugins.py
scriptbook/routers/scripts.py
scriptbook/static/index.html
scriptbook/static/css/main.css
scriptbook/static/js/ansi-html.min.js
scriptbook/static/js/app.js
scriptbook/static/js/plugin-loader.js
scriptbook/static/js/terminal-manager.js
scriptbook/static/js/lib/xterm.css
scriptbook/static/js/lib/xterm.js
scriptbook/static/js/lib/xterm.js.map
scriptbook/static/plugins/theme-github/manifest.json
scriptbook/static/plugins/theme-github/style.css
scriptbook/static/plugins/theme-github-dark/manifest.json
scriptbook/static/plugins/theme-github-dark/style.css
scriptbook-1.6.1.dist-info/METADATA
scriptbook-1.6.1.dist-info/WHEEL
scriptbook-1.6.1.dist-info/entry_points.txt
scriptbook-1.6.1.dist-info/RECORD
