Metadata-Version: 2.4
Name: scriptbook
Version: 1.6.1
Summary: Scriptbook - An executable Markdown server with script execution, result persistence, and stop functionality, ideal for SOP automation
Project-URL: Homepage, https://github.com/lengmoXXL/scriptbook
Project-URL: Repository, https://github.com/lengmoXXL/scriptbook
Project-URL: Issues, https://github.com/lengmoXXL/scriptbook/issues
Author-email: lzy <forlearn_lzy@163.com>
License: MIT
Classifier: Development Status :: 4 - Beta
Classifier: Intended Audience :: Developers
Classifier: License :: OSI Approved :: MIT License
Classifier: Programming Language :: Python :: 3
Classifier: Programming Language :: Python :: 3.10
Classifier: Programming Language :: Python :: 3.11
Classifier: Programming Language :: Python :: 3.12
Classifier: Programming Language :: Python :: 3.13
Classifier: Programming Language :: Python :: 3.14
Requires-Python: >=3.10
Requires-Dist: fastapi>=0.104.0
Requires-Dist: markdown>=3.5
Requires-Dist: pydantic>=2.0.0
Requires-Dist: python-multipart>=0.0.6
Requires-Dist: uvicorn[standard]>=0.24.0
Requires-Dist: watchdog>=3.0
Requires-Dist: websockets>=12.0
Provides-Extra: dev
Requires-Dist: coverage>=7.3.0; extra == 'dev'
Requires-Dist: pytest-asyncio>=1.3.0; extra == 'dev'
Requires-Dist: pytest-cov>=4.1.0; extra == 'dev'
Requires-Dist: pytest-mock>=3.12.0; extra == 'dev'
Requires-Dist: pytest>=9.0.2; extra == 'dev'
